{
  "id": "tz-act-gn-2002-470",
  "type": "statute",
  "title": "Sheria Ndogo za (Hifadhi ya Mazingira na Matumizi Bora ya Ardhi) za Halmashauri ya Wilaya ya Bukombe 2002",
  "title_en": "Sheria Ndogo za (Hifadhi ya Mazingira na Matumizi Bora ya Ardhi) za Halmashauri ya Wilaya ya Bukombe 2002",
  "short_name": "Sheria Ndogo za (Hifadhi ya...",
  "status": "in_force",
  "issued_date": "",
  "in_force_date": "",
  "url": "https://tanzlii.org/en/akn/tz/act/gn/2002/470/eng@2002-10-11",
  "provisions": [],
  "definitions": []
}