{
  "id": "tz-act-gn-2006-4",
  "type": "statute",
  "title": "Transfer of Assets of the Tanesco Training Center to the Muslim Development Foundation (MDF) Instrument of Transfer, 2006",
  "title_en": "Transfer of Assets of the Tanesco Training Center to the Muslim Development Foundation (MDF) Instrument of Transfer, 2006",
  "short_name": "Transfer of Assets of the T...",
  "status": "in_force",
  "issued_date": "",
  "in_force_date": "",
  "url": "https://tanzlii.org/en/akn/tz/act/gn/2006/4/eng@2006-01-20",
  "provisions": [],
  "definitions": []
}