{
  "id": "tz-act-gn-2002-261",
  "type": "statute",
  "title": "Excise Tariff (Exemption) (Upgrading of Muhutwe-Kagoma Road Project) (M/S China Road and Bridge Corporation) Order, 2002",
  "title_en": "Excise Tariff (Exemption) (Upgrading of Muhutwe-Kagoma Road Project) (M/S China Road and Bridge Corporation) Order, 2002",
  "short_name": "Excise Tariff (Exemption) (...",
  "status": "in_force",
  "issued_date": "",
  "in_force_date": "",
  "url": "https://tanzlii.org/en/akn/tz/act/gn/2002/261/eng@2002-06-21",
  "provisions": [],
  "definitions": []
}